README
setup.py
bin/winter_admin.py
bin/winter_ver.py
winter_project/__init__.py
winter_project/core.py
winter_project/main.py
winterstone/__init__.py
winterstone/base.py
winterstone/baseQt.py
winterstone/extraQt.py
winterstone/snowflake.py
winterstone/winterBug.py
winterstone.egg-info/PKG-INFO
winterstone.egg-info/SOURCES.txt
winterstone.egg-info/dependency_links.txt
winterstone.egg-info/requires.txt
winterstone.egg-info/top_level.txt