Metadata-Version: 1.0
Name: winterstone
Version: 0.8.6.7
Summary: Framework for PyQt application
Home-page: http://averrin.github.com/inkmoth
Author: Averrin
Author-email: averrin@gmail.com
License: GPL v3
Keywords: pyqt plugins framework
Platform: UNKNOWN
Classifier: Development Status :: 4 - Beta
Classifier: Topic :: Utilities
Classifier: Environment :: X11 Applications :: Qt
Classifier: Intended Audience :: Developers
Classifier: Programming Language :: Python :: 2
Classifier: Topic :: Software Development :: User Interfaces
Classifier: License :: OSI Approved :: GNU General Public License (GPL)
